Metadata-Version: 2.1
Name: piptoolpeteryang
Version: 0.2
Summary: A tool to manage python dependencies
Author: Peter Yang
